Serial/__init__.py
Serial/version.py
robotframework_serial-0.2.0.dist-info/LICENSE
robotframework_serial-0.2.0.dist-info/METADATA
robotframework_serial-0.2.0.dist-info/WHEEL
robotframework_serial-0.2.0.dist-info/top_level.txt
robotframework_serial-0.2.0.dist-info/RECORD
