Metadata-Version: 2.1
Name: robotframework-serial
Version: 0.2.0
Summary: Robot Framework test library for serial connection
Home-page: https://github.com/Warcaith/robotframework-serial
Author: Fredrik Karlsson
Author-email: f.v.carlsson@gmail.com
License: Apache License 2.0
Keywords: robotframework testing testautomation serial
Platform: any
Classifier: Development Status :: 3 - Alpha
Classifier: License :: OSI Approved :: Apache Software License
Classifier: Operating System :: OS Independent
Classifier: Programming Language :: Python :: 3.9
Classifier: Topic :: Software Development :: Testing
Requires-Dist: robotframework
Requires-Dist: pyserial
